tablefield/__init__.py
tablefield/fields.py
tablefield/locale/ar/LC_MESSAGES/django.mo
tablefield/locale/ar/LC_MESSAGES/django.po
tablefield/locale/be/LC_MESSAGES/django.mo
tablefield/locale/be/LC_MESSAGES/django.po
tablefield/locale/ca/LC_MESSAGES/django.mo
tablefield/locale/ca/LC_MESSAGES/django.po
tablefield/locale/cs/LC_MESSAGES/django.mo
tablefield/locale/cs/LC_MESSAGES/django.po
tablefield/locale/de/LC_MESSAGES/django.mo
tablefield/locale/de/LC_MESSAGES/django.po
tablefield/locale/el/LC_MESSAGES/django.mo
tablefield/locale/el/LC_MESSAGES/django.po
tablefield/locale/en/LC_MESSAGES/django.mo
tablefield/locale/en/LC_MESSAGES/django.po
tablefield/locale/es/LC_MESSAGES/django.mo
tablefield/locale/es/LC_MESSAGES/django.po
tablefield/locale/fa/LC_MESSAGES/django.mo
tablefield/locale/fa/LC_MESSAGES/django.po
tablefield/locale/fi/LC_MESSAGES/django.mo
tablefield/locale/fi/LC_MESSAGES/django.po
tablefield/locale/fr/LC_MESSAGES/django.mo
tablefield/locale/fr/LC_MESSAGES/django.po
tablefield/locale/gl/LC_MESSAGES/django.mo
tablefield/locale/gl/LC_MESSAGES/django.po
tablefield/locale/hu/LC_MESSAGES/django.mo
tablefield/locale/hu/LC_MESSAGES/django.po
tablefield/locale/id_ID/LC_MESSAGES/django.mo
tablefield/locale/id_ID/LC_MESSAGES/django.po
tablefield/locale/is_IS/LC_MESSAGES/django.mo
tablefield/locale/is_IS/LC_MESSAGES/django.po
tablefield/locale/it/LC_MESSAGES/django.mo
tablefield/locale/it/LC_MESSAGES/django.po
tablefield/locale/ja/LC_MESSAGES/django.mo
tablefield/locale/ja/LC_MESSAGES/django.po
tablefield/locale/ko/LC_MESSAGES/django.mo
tablefield/locale/ko/LC_MESSAGES/django.po
tablefield/locale/lt/LC_MESSAGES/django.mo
tablefield/locale/lt/LC_MESSAGES/django.po
tablefield/locale/lv/LC_MESSAGES/django.mo
tablefield/locale/lv/LC_MESSAGES/django.po
tablefield/locale/mn/LC_MESSAGES/django.mo
tablefield/locale/mn/LC_MESSAGES/django.po
tablefield/locale/my/LC_MESSAGES/django.mo
tablefield/locale/my/LC_MESSAGES/django.po
tablefield/locale/nb/LC_MESSAGES/django.mo
django_tablefield-0.0.5.dist-info/LICENSE
django_tablefield-0.0.5.dist-info/METADATA
django_tablefield-0.0.5.dist-info/WHEEL
django_tablefield-0.0.5.dist-info/top_level.txt
django_tablefield-0.0.5.dist-info/RECORD
