Metadata-Version: 2.1
Name: django-tablefield
Version: 0.0.5
Summary: tables in django admin
Home-page: https://github.com/raagin/django-tablefield
Author: Yury Lapshinov
Author-email: y.raagin@gmail.com
License: MIT
Platform: UNKNOWN
Classifier: Development Status :: 5 - Production/Stable
Classifier: Programming Language :: Python :: 3
Classifier: License :: OSI Approved :: MIT License
Classifier: Operating System :: OS Independent
Requires-Python: >=3
License-File: LICENSE
